ado_pipeline_helper/__init__.py
ado_pipeline_helper/cli.py
ado_pipeline_helper/client.py
ado_pipeline_helper/config.py
ado_pipeline_helper/resolver/__init__.py
ado_pipeline_helper/resolver/parameters.py
ado_pipeline_helper/resolver/yaml_loader.py
ado_pipeline_helper/utils.py
ado_pipeline_helper-0.0.1.dist-info/entry_points.txt
ado_pipeline_helper-0.0.1.dist-info/LICENSE
ado_pipeline_helper-0.0.1.dist-info/WHEEL
ado_pipeline_helper-0.0.1.dist-info/METADATA
ado_pipeline_helper-0.0.1.dist-info/RECORD
