Metadata-Version: 2.1
Name: ado-pipeline-helper
Version: 0.0.1
Summary: 
Author: StefanBRas
Author-email: gitcommits@bruhn.io
Requires-Python: >=3.10,<4.0
Classifier: Programming Language :: Python :: 3
Classifier: Programming Language :: Python :: 3.10
Classifier: Programming Language :: Python :: 3.11
Requires-Dist: azure-devops (>=6.0.0b4,<7.0.0)
Requires-Dist: pydantic (>=1.10.2,<2.0.0)
Requires-Dist: pyright (>=1.1.298,<2.0.0)
Requires-Dist: ruamel-yaml (>=0.17.21,<0.18.0)
Requires-Dist: structlog (>=22.3.0,<23.0.0)
Requires-Dist: typer[all] (>=0.7.0,<0.8.0)
